{
  "node": {
    "6029787df4e36c562fd6aadcec67d07f7b5ecb7a05": {
      "workers": {
        "app/ai-assistant/page": {
          "moduleId": 16192,
          "async": false,
          "exportedName": "diagnoseService",
          "filename": "app/actions/diagnose-service.ts"
        }
      },
      "layer": {
        "app/ai-assistant/page": "action-browser"
      },
      "exportedName": "diagnoseService",
      "filename": "app/actions/diagnose-service.ts"
    },
    "60bf64311c281730ff482d5e25a31e2a73159bceeb": {
      "workers": {
        "app/ai-assistant/page": {
          "moduleId": 16192,
          "async": false,
          "exportedName": "chatWithGemini",
          "filename": "app/actions/chat-service.ts"
        }
      },
      "layer": {
        "app/ai-assistant/page": "action-browser"
      },
      "exportedName": "chatWithGemini",
      "filename": "app/actions/chat-service.ts"
    }
  },
  "edge": {}
}